tibetan_wer/__init__.py
tibetan_wer/metrics.py
tibetan_wer-1.0.1.dist-info/METADATA
tibetan_wer-1.0.1.dist-info/WHEEL
tibetan_wer-1.0.1.dist-info/licenses/LICENSE
tibetan_wer-1.0.1.dist-info/RECORD
