Metadata-Version: 2.4
Name: tibetan-wer
Version: 1.0.1
Summary: Compute Word Error Rate for Tibetan language text.
Project-URL: Homepage, https://github.com/billingsmoore/tibetan-wer
Project-URL: Issues, https://github.com/billingsmoore/tibetan-wer/issues
Author-email: billingsmoore <billingsmoore@gmail.com>
License-File: LICENSE
Classifier: License :: OSI Approved :: Apache Software License
Classifier: Operating System :: OS Independent
Classifier: Programming Language :: Python :: 3
Requires-Python: >=3.8
Requires-Dist: botok
Requires-Dist: numpy
